{
  "bracelet_exchange": "BRACELET_EXCHANGE",
  "smoking": "SMOKE",
  "thirst": "GO_FOR_DRINK",
  "sitting": "SIT",
  "hunger": "GO_FOR_FOOD",
  "wc": "GO_TO_TOILET",
  "dirty_hand": "WASH",
  "brushing_teeth": "BRUSH_TEETH",
  "low_money": "WITHDRAW",
  "cup_return": "RETURN_CUP",
  "want_merch": "BUY_MERCH",
  "meet_band": "GO_TO_SIGNING_SESSION",
  "phone_dead": "CHARGE_PHONE",
  "band_playing": "GO_TO_CONCERT",
  "living": "PITCH_TENT",
  "energy": "SLEEP_IN_TENT",
  "hygiene": "GO_TO_SHOWER",
  "smoking_water_pipe": "GO_SMOKE_WATER_PIPE",
  "tiredness": "GO_CHILL",
  "low_cigars": "BUY_CIGARS",
  "attraction_desire": "GO_TO_ATTRACTION"
}